{
  "scenes": [
    {
      "bg": "assets2/bg001.png",
      "characters": [
        { "side": "center", "src": "assets2/a03002.png" }
      ],
      "name": "翠",
      "text": "こんにちは。今日もよろしくお願いします。",
      "speed": 30,
      "fontSize": "1.2em",
      "choices": [
        { "text": "はい、頑張りましょう", "next": 1 }
      ]
    },
    {
      "bg": "assets2/bg002.png",
      "characters": [
        { "side": "left", "src": "assets2/a04002.png" },
        { "side": "right", "src": "assets2/a05002.png" }
      ],
      "name": "こがね",
      "text": "わたし達もがんばるよー！",
      "speed": 50,
      "fontSize": "1em",
      "choices": []
    }
  ]
}
